azure/appconfiguration/__init__.py
azure/appconfiguration/_azure_appconfiguration_client.py
azure/appconfiguration/_azure_appconfiguration_error.py
azure/appconfiguration/_azure_appconfiguration_requests.py
azure/appconfiguration/_constants.py
azure/appconfiguration/_models.py
azure/appconfiguration/_sync_token.py
azure/appconfiguration/_utils.py
azure/appconfiguration/_version.py
azure/appconfiguration/py.typed
azure/appconfiguration/_generated/__init__.py
azure/appconfiguration/_generated/_azure_app_configuration.py
azure/appconfiguration/_generated/_configuration.py
azure/appconfiguration/_generated/_patch.py
azure/appconfiguration/_generated/_serialization.py
azure/appconfiguration/_generated/_vendor.py
azure/appconfiguration/_generated/py.typed
azure/appconfiguration/_generated/aio/__init__.py
azure/appconfiguration/_generated/aio/_azure_app_configuration.py
azure/appconfiguration/_generated/aio/_configuration.py
azure/appconfiguration/_generated/aio/_patch.py
azure/appconfiguration/_generated/aio/_vendor.py
azure/appconfiguration/_generated/aio/operations/__init__.py
azure/appconfiguration/_generated/aio/operations/_azure_app_configuration_operations.py
azure/appconfiguration/_generated/aio/operations/_patch.py
azure/appconfiguration/_generated/models/__init__.py
azure/appconfiguration/_generated/models/_azure_app_configuration_enums.py
azure/appconfiguration/_generated/models/_models_py3.py
azure/appconfiguration/_generated/models/_patch.py
azure/appconfiguration/_generated/operations/__init__.py
azure/appconfiguration/_generated/operations/_azure_app_configuration_operations.py
azure/appconfiguration/_generated/operations/_patch.py
azure/appconfiguration/aio/__init__.py
azure/appconfiguration/aio/_azure_appconfiguration_client_async.py
azure/appconfiguration/aio/_sync_token_async.py
azure_appconfiguration-1.7.1.dist-info/LICENSE
azure_appconfiguration-1.7.1.dist-info/METADATA
azure_appconfiguration-1.7.1.dist-info/WHEEL
azure_appconfiguration-1.7.1.dist-info/top_level.txt
azure_appconfiguration-1.7.1.dist-info/RECORD
