Metadata-Version: 2.1
Name: azure-appconfiguration
Version: 1.7.1
Summary: Microsoft App Configuration Data Library for Python
Home-page: https://github.com/Azure/azure-sdk-for-python/tree/main/sdk/appconfiguration/azure-appconfiguration
Author: Microsoft Corporation
Author-email: azpysdkhelp@microsoft.com
License: MIT License
Keywords: azure,azure sdk
Classifier: Development Status :: 5 - Production/Stable
Classifier: Programming Language :: Python
Classifier: Programming Language :: Python :: 3 :: Only
Classifier: Programming Language :: Python :: 3
Classifier: Programming Language :: Python :: 3.8
Classifier: Programming Language :: Python :: 3.9
Classifier: Programming Language :: Python :: 3.10
Classifier: Programming Language :: Python :: 3.11
Classifier: Programming Language :: Python :: 3.12
Classifier: License :: OSI Approved :: MIT License
Requires-Python: >=3.8
License-File: LICENSE
Requires-Dist: azure-core>=1.28.0
Requires-Dist: isodate>=0.6.0
